{
  "version": "6",
  "dialect": "postgresql",
  "entries": [
    {
      "idx": 0,
      "version": "6",
      "when": 1716983496291,
      "tag": "0000_cooing_red_ghost",
      "breakpoints": true
    },
    {
      "idx": 1,
      "version": "6",
      "when": 1716984048713,
      "tag": "0001_parallel_human_cannonball",
      "breakpoints": true
    },
    {
      "idx": 2,
      "version": "6",
      "when": 1716987233460,
      "tag": "0002_chief_titania",
      "breakpoints": true
    },
    {
      "idx": 3,
      "version": "6",
      "when": 1716992449422,
      "tag": "0003_sturdy_sir_ram",
      "breakpoints": true
    },
    {
      "idx": 4,
      "version": "6",
      "when": 1716992488644,
      "tag": "0004_previous_zemo",
      "breakpoints": true
    }
  ]
}